[
  {
    "message": "Everything you need to ace KWoC",
    "url": "https://medium.com/kharagpur-open-source-society/an-informal-introduction-to-kwoc-62fc5e686f79",
    "avatar": "https://raw.githubusercontent.com/kossiitkgp/design/master/logo/koss/main/koss-logo.svg"
  },
  {
    "message": "Codeacademy: Learn Git",
    "url": "https://www.codecademy.com/learn/learn-git",
    "avatar": "https://www.codecademy.com/favicon.ico",
    "noAvatarRounding": true
  },
  {
    "message": "Git Flight Rules: Cookbook for Git",
    "url": "https://github.com/k88hudson/git-flight-rules",
    "avatar": "https://github.com/k88hudson.png"
  },
  {
    "message": "GitHub: Hello World Tutorial",
    "url": "https://guides.github.com/activities/hello-world/",
    "avatar": "https://github.com/github.png"
  }
]
